setup.py
persistent_ordered_dict.egg-info/PKG-INFO
persistent_ordered_dict.egg-info/SOURCES.txt
persistent_ordered_dict.egg-info/dependency_links.txt
persistent_ordered_dict.egg-info/top_level.txt
pod/__init__.py
pod/file_utils.py
pod/p.py