Metadata-Version: 1.1
Name: persistent-ordered-dict
Version: 0.0.2
Summary: a transparently persisted datastructure
Home-page: https://github.com/enewe101/persistent-ordered-dict
Author: Edward Newell
Author-email: edward.newell@gmail.com
License: MIT
Keywords: data structure,storage,synchronized,dictionary,collection
Platform: UNKNOWN
Classifier: Development Status :: 3 - Alpha
Classifier: Intended Audience :: Developers
Classifier: Topic :: Software Development :: Build Tools
Classifier: License :: OSI Approved :: MIT License
Classifier: Programming Language :: Python :: 2.7
